batchnormlstm/__init__.py
batchnormlstm/gradient_check.py
batchnormlstm/layer_utils.py
batchnormlstm/layers.py
batchnormlstm/optim.py
batchnormlstm/solver.py
batchnormlstm/classifiers/__init__.py
batchnormlstm/classifiers/lstm.py
batchnorm_lstm-0.0.1.dist-info/LICENSE
batchnorm_lstm-0.0.1.dist-info/METADATA
batchnorm_lstm-0.0.1.dist-info/WHEEL
batchnorm_lstm-0.0.1.dist-info/top_level.txt
batchnorm_lstm-0.0.1.dist-info/RECORD
